nitroexpose/__init__.py
nitroexpose/cli.py
nitroexpose-2.7.dist-info/licenses/LICENCE
nitroexpose-2.7.dist-info/METADATA
nitroexpose-2.7.dist-info/WHEEL
nitroexpose-2.7.dist-info/entry_points.txt
nitroexpose-2.7.dist-info/top_level.txt
nitroexpose-2.7.dist-info/RECORD
