Metadata-Version: 2.4
Name: NitroExpose
Version: 2.7
Summary: Advanced CLI To Expose Port To Your Domain.
Home-page: https://github.com/yuvrajmodz/NitroExpose
Author: @NacDevs
Author-email: yuvrajmodz@gmail.com
Classifier: Programming Language :: Python :: 3
Classifier: License :: OSI Approved :: MIT License
Classifier: Operating System :: POSIX :: Linux
Requires-Python: >=3.8
License-File: LICENCE
Requires-Dist: requests
Requires-Dist: supercore
Requires-Dist: uvloop
Requires-Dist: httptools
Dynamic: author
Dynamic: author-email
Dynamic: classifier
Dynamic: description
Dynamic: description-content-type
Dynamic: home-page
Dynamic: license-file
Dynamic: requires-dist
Dynamic: requires-python
Dynamic: summary
